pyqt_drawer/__init__.py
pyqt_drawer/drawer.py
pyqt_drawer/ico/__init__.py
pyqt_drawer/ico/drawer.svg
pyqt_drawer-0.0.17.dist-info/LICENSE
pyqt_drawer-0.0.17.dist-info/METADATA
pyqt_drawer-0.0.17.dist-info/WHEEL
pyqt_drawer-0.0.17.dist-info/top_level.txt
pyqt_drawer-0.0.17.dist-info/RECORD
