Metadata-Version: 2.1
Name: pyqt-drawer
Version: 0.0.17
Summary: PyQt drawer
Home-page: https://github.com/yjg30737/pyqt-drawer.git
Author: Jung Gyu Yoon
Author-email: yjg30737@gmail.com
License: MIT
Platform: UNKNOWN
License-File: LICENSE
Requires-Dist: PyQt5 (>=5.8)
Requires-Dist: pyqt-svg-button (>=0.0.1)
